{
  "code": "10.3.4",
  "title": "تقييم الأصول والالتزامات",
  "slug": "valuation-of-assets-and-liabilities",
  "order": 4,
  "tabs": [
    {
      "code": "theory",
      "title": "الشرح النظري",
      "type": "markdown",
      "file": "theory.md"
    },
    {
      "code": "examples",
      "title": "الأمثلة",
      "type": "markdown",
      "file": "examples.md"
    },
    {
      "code": "essay",
      "title": "أسئلة مقالية",
      "type": "markdown",
      "file": "essay.md"
    },
    {
      "code": "mistakes",
      "title": "أخطاء شائعة",
      "type": "markdown",
      "file": "mistakes.md"
    },
    {
      "code": "mcq",
      "title": "اختيار من متعدد",
      "type": "quiz",
      "file": "mcq.json"
    }
  ]
}
