[
  {
    "level": 1,
    "question": "في المنشأة غير الربحية، صافي الأصول يمثل عادة:",
    "choices": [
      "إجمالي الإيرادات",
      "المتبقي بعد طرح الالتزامات من الأصول",
      "النقدية فقط",
      "الالتزامات طويلة الأجل"
    ],
    "correct": 1,
    "explanation": "هذا هو الجوهر المفاهيمي لصافي الأصول أو الرصيد المقابل لحقوق الملكية."
  },
  {
    "level": 1,
    "question": "أي معيار يدعم منطق العرض الواضح لهذه المفردة؟",
    "choices": [
      "IAS 1",
      "IAS 38",
      "IFRS 3",
      "IAS 16"
    ],
    "correct": 0,
    "explanation": "IAS 1 يدعم العرض المنظم والواضح والإفصاح الملائم."
  },
  {
    "level": 1,
    "question": "صافي الأصول غير المقيدة يعني عادة:",
    "choices": [
      "موارد حرة نسبيًا للاستخدام العام",
      "التزامات مستحقة",
      "أصول غير ملموسة",
      "تبرعات لم تستلم بعد"
    ],
    "correct": 0,
    "explanation": "الموارد غير المقيدة هي التي لا تخضع لقيد خارجي محدد."
  },
  {
    "level": 1,
    "question": "الرصيد المقيد في المنشأة غير الربحية يعني بالضرورة:",
    "choices": [
      "وجود التزام محاسبي",
      "منع استخدام المورد لأي غرض مستقبلاً",
      "وجود قيد على استخدام المورد",
      "اختفاء صافي الأصول"
    ],
    "correct": 2,
    "explanation": "القيد يعني تحديد كيفية الاستخدام، لكنه لا يعني دائمًا التزامًا."
  },
  {
    "level": 1,
    "question": "المعادلة الأساسية لصافي الأصول هي:",
    "choices": [
      "الأصول + الالتزامات",
      "الأصول - الالتزامات",
      "الإيرادات - المصروفات",
      "الأصول - النقدية"
    ],
    "correct": 1,
    "explanation": "صافي الأصول هو المتبقي بعد خصم الالتزامات من الأصول."
  },
  {
    "level": 1,
    "question": "التخصيص الإداري الداخلي يختلف عن القيد الخارجي لأن الأول:",
    "choices": [
      "يفرضه مانح خارجي",
      "ينشأ بقرار من الإدارة",
      "يعد التزامًا قانونيًا دائمًا",
      "يلغي صافي الأصول"
    ],
    "correct": 1,
    "explanation": "التخصيص الداخلي مصدره الإدارة لا طرف خارجي."
  },
  {
    "level": 1,
    "question": "أي من الآتي يعد خطأً شائعًا في هذا الموضوع؟",
    "choices": [
      "التمييز بين المقيد وغير المقيد",
      "القول إن كل مورد مقيد هو التزام",
      "ربط المفردة بالإطار المفاهيمي",
      "طرح الالتزامات من الأصول"
    ],
    "correct": 1,
    "explanation": "هذا من أكثر الأخطاء المفاهيمية تكرارًا."
  },
  {
    "level": 1,
    "question": "الفائض في المنشأة غير الربحية يؤدي غالبًا إلى:",
    "choices": [
      "زيادة صافي الأصول",
      "إلغاء القيود",
      "زيادة الالتزامات دائمًا",
      "تحويل جميع الأرصدة إلى نقدية"
    ],
    "correct": 0,
    "explanation": "الفائض يزيد الرصيد المتبقي ما لم توجد معالجة خاصة تخالف ذلك."
  },
  {
    "level": 1,
    "question": "أي أساس دولي هو الأهم في فهم الفرق بين المورد المقيد والالتزام؟",
    "choices": [
      "الإطار المفاهيمي الدولي",
      "IAS 38",
      "IFRS 3",
      "IAS 2"
    ],
    "correct": 0,
    "explanation": "الإطار المفاهيمي يوضح معنى الالتزام وحقوق الملكية أو المتبقي."
  },
  {
    "level": 1,
    "question": "العرض الجيد لصافي الأصول في المنشأة غير الربحية يركز على:",
    "choices": [
      "الرقم الإجمالي فقط",
      "طبيعة الرصيد وقيوده",
      "النقدية فقط",
      "تفاصيل المخزون فقط"
    ],
    "correct": 1,
    "explanation": "طبيعة الرصيد لا تقل أهمية عن مقداره."
  },
  {
    "level": 2,
    "question": "إذا كانت أصول منشأة غير ربحية 800,000 ريال والتزاماتها 300,000 ريال، فإن صافي الأصول يساوي:",
    "choices": [
      "500,000 ريال",
      "1,100,000 ريال",
      "300,000 ريال",
      "800,000 ريال"
    ],
    "correct": 0,
    "explanation": "800,000 - 300,000 = 500,000 ريال."
  },
  {
    "level": 2,
    "question": "إذا كان صافي الأصول 600,000 ريال، منها 150,000 ريال مقيدة، فإن الجزء غير المقيد يساوي:",
    "choices": [
      "150,000 ريال",
      "450,000 ريال",
      "600,000 ريال",
      "750,000 ريال"
    ],
    "correct": 1,
    "explanation": "600,000 - 150,000 = 450,000 ريال."
  },
  {
    "level": 2,
    "question": "تلقت المنشأة تبرعًا غير مقيد 40,000 ريال. الأثر الأكثر مباشرة يكون على:",
    "choices": [
      "صافي الأصول غير المقيدة",
      "الالتزامات طويلة الأجل",
      "الأصول غير الملموسة",
      "الشهرة"
    ],
    "correct": 0,
    "explanation": "لأن المورد غير مقيد ويزيد الرصيد غير المقيد."
  },
  {
    "level": 2,
    "question": "إذا خصصت الإدارة 30,000 ريال للطوارئ بقرار داخلي، فإن هذا يعد:",
    "choices": [
      "قيدًا خارجيًا",
      "تخصيصًا إداريًا داخليًا",
      "التزامًا مستحقًا",
      "إلغاءً لصافي الأصول"
    ],
    "correct": 1,
    "explanation": "لأن مصدره الإدارة لا مانح خارجي."
  },
  {
    "level": 2,
    "question": "أي عبارة أدق بخصوص الموارد المقيدة؟",
    "choices": [
      "تعد التزامات دائمًا",
      "لا تظهر ضمن صافي الأصول مطلقًا",
      "قد تبقى ضمن صافي الأصول مع الإفصاح عن القيد",
      "تساوي المصروفات المؤجلة"
    ],
    "correct": 2,
    "explanation": "القيد على المورد لا يعني خروجه تلقائيًا من صافي الأصول."
  },
  {
    "level": 2,
    "question": "إذا حققت المنشأة عجزًا خلال السنة، فإن الأثر الأكثر احتمالًا على صافي الأصول هو:",
    "choices": [
      "الزيادة",
      "عدم التغير مطلقًا",
      "الانخفاض",
      "التحول إلى التزام"
    ],
    "correct": 2,
    "explanation": "العجز يخفض صافي الأصول."
  },
  {
    "level": 2,
    "question": "ما الهدف من الفصل بين المقيد وغير المقيد في العرض؟",
    "choices": [
      "زيادة عدد البنود فقط",
      "إظهار المرونة الفعلية في استخدام الموارد",
      "تحويل المنشأة إلى ربحية",
      "تجنب الإفصاح"
    ],
    "correct": 1,
    "explanation": "هذا الفصل يوضح قدرة المنشأة على استخدام الموارد بحرية أو عدمها."
  },
  {
    "level": 2,
    "question": "إذا كان مورد ما مقيدًا بمشروع تعليمي، فإن الخطأ الشائع هو:",
    "choices": [
      "إفصاح القيد",
      "عرضه ضمن المقيد",
      "اعتباره التزامًا تلقائيًا",
      "ربطه بالعرض"
    ],
    "correct": 2,
    "explanation": "هذا من الأخطاء المفاهيمية الأكثر شيوعًا."
  },
  {
    "level": 2,
    "question": "أي معيار أقل ارتباطًا مباشرة بهذه المفردة مقارنة بالمعايير الأخرى؟",
    "choices": [
      "IAS 1",
      "الإطار المفاهيمي",
      "IAS 38",
      "منطق العرض والإفصاح"
    ],
    "correct": 2,
    "explanation": "IAS 38 يتعلق بالأصول غير الملموسة، وليس المرجع الأقرب لهذه المفردة."
  },
  {
    "level": 2,
    "question": "إذا أريد عرض الرصيد المتبقي للمنشأة غير الربحية بصورة مهنية، فإن الأفضل هو:",
    "choices": [
      "إخفاء القيود لعدم التعقيد",
      "عرض طبيعة الرصيد مع التفصيل الملائم",
      "إلغاء كل التبويبات",
      "الاكتفاء برقم الأصول"
    ],
    "correct": 1,
    "explanation": "العرض المهني يبين طبيعة الرصيد وحدود استخدامه."
  },
  {
    "level": 3,
    "question": "بلغت أصول منشأة غير ربحية 1,200,000 ريال والتزاماتها 450,000 ريال. وكان من صافي الأصول 300,000 ريال مقيدة و50,000 ريال مخصصة داخليًا. ما العبارة الأدق؟",
    "choices": [
      "جميع الـ 350,000 ريال التزام",
      "صافي الأصول 750,000 ريال، منها 300,000 مقيدة خارجيًا و50,000 مخصصة داخليًا",
      "صافي الأصول 700,000 ريال فقط",
      "لا يمكن التمييز بين الرصيدين"
    ],
    "correct": 1,
    "explanation": "صافي الأصول = 1,200,000 - 450,000 = 750,000 ريال، مع التمييز بين القيد الخارجي والتخصيص الداخلي."
  },
  {
    "level": 3,
    "question": "قال طالب: بما أن التبرع مخصص لبرنامج طبي فلا بد أن يعرض كله كالتزام. ما الخطأ الأساسي في هذا الرأي؟",
    "choices": [
      "الخلط بين القيد على الاستخدام وبين تعريف الالتزام",
      "الخلط بين الأصول والنقدية فقط",
      "الخلط بين IAS 1 وIAS 38",
      "الخلط بين الإيراد والمخزون"
    ],
    "correct": 0,
    "explanation": "وجود قيد على الاستخدام لا يعني بالضرورة تحقق تعريف الالتزام."
  },
  {
    "level": 3,
    "question": "إذا تلقت المنشأة 100,000 ريال لمشروع محدد و20,000 ريال تبرعًا عامًا، فإن العرض المهني الأنسب هو:",
    "choices": [
      "جمع المبلغين ضمن الالتزامات",
      "عرض المبلغين ضمن المقيد فقط",
      "عرض 100,000 ضمن المقيد و20,000 ضمن غير المقيد",
      "إهمال التفصيل"
    ],
    "correct": 2,
    "explanation": "لأن طبيعة الموردين مختلفة من حيث القيد."
  },
  {
    "level": 3,
    "question": "إذا حققت المنشأة فائضًا 70,000 ريال، واستخدمت 40,000 ريال من موارد مقيدة في غرضها المحدد، فإن الفهم الأدق هو:",
    "choices": [
      "لا يتأثر صافي الأصول إطلاقًا",
      "يتأثر صافي الأصول وحركتهما حسب طبيعة الفائض واستخدام الموارد المقيدة",
      "تتحول كل الموارد المقيدة إلى التزامات",
      "ينبغي إلغاء التمييز بين المقيد وغير المقيد"
    ],
    "correct": 1,
    "explanation": "الفائض يؤثر في الرصيد المتبقي، واستخدام الموارد المقيدة يؤثر في تبويبها أو رصيدها المقيد."
  },
  {
    "level": 3,
    "question": "ما الخطأ في مساواة التخصيص الإداري الداخلي بالقيد الخارجي؟",
    "choices": [
      "تجاهل مصدر التقييد",
      "تجاهل النقدية فقط",
      "تجاهل المصروفات التشغيلية",
      "تجاهل الأصول الثابتة"
    ],
    "correct": 0,
    "explanation": "مصدر التقييد هو الفارق الجوهري بين الحالتين."
  },
  {
    "level": 3,
    "question": "إذا عرضت المنشأة صافي أصولها كرقم واحد مع وجود قيود جوهرية، فإن المشكلة الرئيسة هي:",
    "choices": [
      "تضخيم الأصول",
      "ضعف الإفصاح وفهم المرونة المالية",
      "زيادة الالتزامات",
      "اختفاء الفائض"
    ],
    "correct": 1,
    "explanation": "العرض المجمل قد يخفي حقيقة الموارد المتاحة فعليًا."
  },
  {
    "level": 3,
    "question": "أي من الآتي يمثل تطبيقًا سليمًا للإطار المفاهيمي على المنشأة غير الربحية؟",
    "choices": [
      "إلغاء مفهوم المتبقي",
      "اعتبار صافي الأصول متبقيًا بعد الالتزامات",
      "اعتبار كل صافي الأصول أصلًا",
      "اعتبار كل تبرع التزامًا"
    ],
    "correct": 1,
    "explanation": "هذا هو التطبيق المفاهيمي الصحيح على البيئة غير الربحية."
  },
  {
    "level": 3,
    "question": "إذا تغيّر عرض صافي الأصول بين سنتين بسبب تحسين التبويب فقط، فإن التصنيف الأدق للحالة هو:",
    "choices": [
      "خطأ سابق دائمًا",
      "قد يكون تحسين عرض لا يستلزم وصفه كخطأ سابق تلقائيًا",
      "حالة IAS 38",
      "حالة IFRS 3"
    ],
    "correct": 1,
    "explanation": "ليس كل اختلاف في العرض يعني بالضرورة وجود خطأ سابق."
  },
  {
    "level": 3,
    "question": "أي عبارة أدق عن علاقة الفائض أو العجز بصافي الأصول؟",
    "choices": [
      "لا توجد علاقة",
      "الفائض يزيده والعجز يخفضه",
      "العجز يزيده",
      "الفائض يحوله إلى التزام"
    ],
    "correct": 1,
    "explanation": "نتيجة الفترة تؤثر في الرصيد المتبقي للمنشأة."
  },
  {
    "level": 3,
    "question": "عند تحليل رصيد صافي الأصول في منشأة غير ربحية، فإن المعلومة الأكثر أهمية بعد الرقم الإجمالي هي:",
    "choices": [
      "نوع المبنى",
      "تفصيل القيود وطبيعة استخدام الموارد",
      "عدد الموظفين فقط",
      "تكلفة الإهلاك فقط"
    ],
    "correct": 1,
    "explanation": "طبيعة الموارد وقيودها عنصر حاسم في فهم المركز المالي."
  },
  {
    "level": 4,
    "question": "أي عبارة تعكس الفهم الأدق لمفهوم حقوق الملكية في المنشأة غير الربحية؟",
    "choices": [
      "لا وجود لمفهوم المتبقي أصلًا",
      "يوجد متبقٍّ مفاهيمي قد يعرض كصافي أصول أو أرصدة صناديق وفق طبيعة المنشأة",
      "كل صافي الأصول يساوي نقدية",
      "كل صافي الأصول التزام محتمل"
    ],
    "correct": 1,
    "explanation": "هذا هو الفهم المفاهيمي الأدق في البيئة غير الربحية."
  },
  {
    "level": 4,
    "question": "ما الخطأ الجوهري في العبارة: \"كل مورد مقيد يجب أن يظهر ضمن الالتزامات\"؟",
    "choices": [
      "الخلط بين القيد الخارجي والتزام الأداء أو الواجب الحالي",
      "الخلط بين الاحتياطيات والأصول الثابتة",
      "الخلط بين IAS 38 وIAS 16",
      "الخلط بين النقدية والمخزون"
    ],
    "correct": 0,
    "explanation": "وجود قيد على الاستخدام لا يحقق وحده تعريف الالتزام في الإطار المفاهيمي."
  },
  {
    "level": 4,
    "question": "أي خيار هو الأكثر مهنية عند وجود موارد مقيدة داخليًا وأخرى مقيدة خارجيًا؟",
    "choices": [
      "دمجهما في بند واحد بلا شرح",
      "إظهار التمييز بينهما لأن مصدر القيد وأثره مختلفان",
      "اعتبارهما التزامًا واحدًا",
      "إلغاء التبويب كليًا"
    ],
    "correct": 1,
    "explanation": "المصدر المختلف للقيد يفرض تمييزًا مهنيًا في العرض."
  },
  {
    "level": 4,
    "question": "أي من الآتي يكشف خلطًا غير صحيح مع IAS 8؟",
    "choices": [
      "اعتبار كل تغير في العرض أو التبويب خطأً سابقًا بالضرورة",
      "فحص ما إذا كانت الحالة تصحيح خطأ أم مجرد تحسين عرض",
      "التمييز بين الخطأ وبين التطوير في العرض",
      "الرجوع إلى الإطار المفاهيمي عند التصنيف"
    ],
    "correct": 0,
    "explanation": "IAS 8 لا يطبق تلقائيًا على كل تغير في العرض أو التبويب."
  },
  {
    "level": 4,
    "question": "أي من الآتي يكشف خلطًا غير صحيح مع IAS 38؟",
    "choices": [
      "اعتبار صافي الأصول أصلًا غير ملموسًا لمجرد أنه غير مادي",
      "التمييز بين الرصيد المتبقي وبين الأصل المعترف به",
      "ربط المفردة بالإطار المفاهيمي",
      "عدم مساواة صافي الأصول بالأصل غير الملموس"
    ],
    "correct": 0,
    "explanation": "الرصيد المتبقي لا يساوي أصلًا غير ملموس."
  },
  {
    "level": 4,
    "question": "أي من الآتي يكشف خلطًا غير صحيح مع IFRS 3؟",
    "choices": [
      "تفسير كل تغير في رصيد صافي الأصول بمنطق تجميع الأعمال",
      "تمييز موضوع العرض في المنشأة غير الربحية عن موضوع الاندماج",
      "الرجوع إلى الإطار المفاهيمي أولًا",
      "حصر IFRS 3 في موضوع تجميع الأعمال"
    ],
    "correct": 0,
    "explanation": "ليس كل تغير في الرصيد المتبقي حالة اندماج أو تجميع أعمال."
  },
  {
    "level": 4,
    "question": "أي قراءة هي الأدق إذا كان إجمالي صافي الأصول مرتفعًا لكن أكثره مقيد؟",
    "choices": [
      "المنشأة تملك مرونة مالية كاملة",
      "الرقم الإجمالي وحده لا يكفي لفهم قدرة المنشأة على التصرف في الموارد",
      "القيود غير مهمة في التحليل",
      "هذا يعني عدم وجود التزامات"
    ],
    "correct": 1,
    "explanation": "قد يكون الرصيد الكلي مرتفعًا لكن الجزء المتاح للاستخدام العام محدودًا."
  },
  {
    "level": 4,
    "question": "إذا عرضت المنشأة صافي الأصول دون أي تفصيل رغم أن التبرعات المقيدة تمثل غالبية الرصيد، فإن الخلل الأكبر يكون في:",
    "choices": [
      "القابلية للفهم والإفصاح الملائم",
      "قيمة الأصول نفسها",
      "طريقة إهلاك الأصول",
      "احتساب التدفقات النقدية"
    ],
    "correct": 0,
    "explanation": "المشكلة الأساسية هنا هي ضعف الإفصاح وجودة العرض."
  },
  {
    "level": 4,
    "question": "أي عبارة ختامية هي الأدق بخصوص هذه المفردة؟",
    "choices": [
      "هي مجرد إعادة تسمية لا أثر لها",
      "هي مفردة تتطلب فهمًا للمتبقي وطبيعة القيود وطريقة العرض، لا مجرد حفظ رقم إجمالي",
      "هي فرع من الأصول غير الملموسة",
      "هي فرع من الالتزامات المتداولة"
    ],
    "correct": 1,
    "explanation": "هذا الوصف يجمع جوهر المفردة كما ينبغي فهمها وعرضها."
  },
  {
    "level": 4,
    "question": "أي موقف يعكس الفهم الأكثر مهنية عند قراءة قائمة مركز مالي لمنشأة غير ربحية يظهر فيها صافي أصول كبير لكن معظمها مقيد لمشاريع محددة؟",
    "choices": [
      "استنتاج أن المنشأة تملك سيولة تشغيلية حرة مرتفعة تلقائيًا",
      "التركيز على الرقم الإجمالي فقط وإهمال القيود",
      "التمييز بين القوة الظاهرية للرصيد وبين حدود استخدامه الفعلية قبل الحكم على المرونة المالية",
      "اعتبار كل الرصيد التزامًا"
    ],
    "correct": 2,
    "explanation": "هذا هو التحليل المهني الأدق لأن فهم صافي الأصول في المنشأة غير الربحية لا يكتمل دون النظر إلى طبيعة القيود ومدى حرية استخدام الموارد."
  }
]
