[
  {
    "question": "ما المقصود بالاعتراف بالمصروفات؟",
    "choices": [
      "إثبات المصروف في الفترة التي يخصها اقتصاديا",
      "إثبات المصروف فقط عند الدفع النقدي",
      "إثبات كل نفقة كأصل",
      "إلغاء تأثير المصروفات من قائمة الدخل"
    ],
    "correct": 0,
    "explanation": "الاعتراف بالمصروفات يعني تحميل الفترة بما يخصها من أعباء وفقا لأساس الاستحقاق."
  },
  {
    "question": "أساس الاستحقاق يعني أن المصروف:",
    "choices": [
      "يعترف به عندما يخص الفترة لا عندما يدفع فقط",
      "لا يعترف به إلا بعد القبض من العميل",
      "يعترف به فقط إذا خرجت نقدية",
      "يحول دائما إلى أصل"
    ],
    "correct": 0,
    "explanation": "الاستحقاق يربط الاعتراف بالفترة التي تتحمل العبء اقتصاديا، لا بموعد السداد النقدي فقط."
  },
  {
    "question": "أي من الآتي يمثل مثالا على مصروف مستحق؟",
    "choices": [
      "رواتب تخص ديسمبر ولم تدفع إلا في يناير",
      "شراء أصل ثابت يستخدم لخمس سنوات",
      "رأس مال مدفوع من الملاك",
      "تحصيل دفعة مقدمة من عميل"
    ],
    "correct": 0,
    "explanation": "الرواتب المستحقة مثال واضح على مصروف يعترف به قبل الدفع."
  },
  {
    "question": "إذا دفعت المنشأة إيجار سنة مقدما، فإن المبلغ كله في تاريخ الدفع:",
    "choices": [
      "يعد مصروفا فوريا بالكامل",
      "قد يعامل كأصل مدفوع مقدما ثم يحمل تدريجيا كمصروف",
      "يعد تكلفة مبيعات",
      "يعد ربحا"
    ],
    "correct": 1,
    "explanation": "الدفع المقدم عن منفعة مستقبلية لا يعد كله مصروفا فوريا، بل يوزع على الفترات المستفيدة."
  },
  {
    "question": "تكلفة المخزون تعترف كمصروف عندما:",
    "choices": [
      "يشترى المخزون",
      "يباع المخزون وتستهلك منفعته الاقتصادية",
      "يدفع ثمنه فقط",
      "يستلم في المخزن فقط"
    ],
    "correct": 1,
    "explanation": "المخزون يظل أصلا حتى البيع، وعندها تتحول تكلفته إلى تكلفة مبيعات."
  },
  {
    "question": "أي معيار يرتبط مباشرة بتحول المخزون إلى تكلفة مبيعات؟",
    "choices": [
      "IAS 2",
      "IAS 1",
      "IAS 16",
      "IFRS 16"
    ],
    "correct": 0,
    "explanation": "`IAS 2` ينظم المخزون، ومنه يفهم توقيت الاعتراف بتكلفة المبيعات."
  },
  {
    "question": "إذا اشترت المنشأة آلة تستخدم لعدة سنوات، فإن التكلفة:",
    "choices": [
      "تحمل كلها كمصروف فوريا",
      "تثبت أصلا ثم توزع على الفترات المستفيدة",
      "لا تظهر في القوائم أبدا",
      "تعامل كتوزيعات أرباح"
    ],
    "correct": 1,
    "explanation": "الأصل طويل الأجل يثبت أصلا ثم يوزع أثره كمصروف على فترات متعددة من خلال الإهلاك أو الإطفاء."
  },
  {
    "question": "أي من الآتي يعبر عن الفرق بين المصروف والأصل؟",
    "choices": [
      "الأصل يحقق منفعة مستقبلية، أما المصروف فيخص الفترة الحالية أو المنفعة المستهلكة",
      "لا يوجد فرق بينهما",
      "المصروف يظهر في المركز المالي دائما",
      "الأصل لا يقاس محاسبيا"
    ],
    "correct": 0,
    "explanation": "هذا هو الفرق الأساسي بين الأصل والمصروف من زاوية الاعتراف المحاسبي."
  },
  {
    "question": "أي معيار يرتبط أكثر بعرض المصروفات في قائمة الربح أو الخسارة؟",
    "choices": [
      "IAS 1",
      "IAS 2",
      "IAS 7",
      "IFRS 15"
    ],
    "correct": 0,
    "explanation": "`IAS 1` ينظم عرض المصروفات بحسب الوظيفة أو الطبيعة داخل قائمة الربح أو الخسارة."
  },
  {
    "question": "إذا أهملت المنشأة مصروفا مستحقا يخص الفترة، فإن صافي الربح غالبا:",
    "choices": [
      "سيظهر أعلى من الواقع",
      "سيظهر أقل من الواقع دائما",
      "لن يتأثر",
      "سيتحول إلى أصل"
    ],
    "correct": 0,
    "explanation": "إهمال مصروف يخص الفترة يؤدي إلى تضخيم صافي الربح."
  },
  {
    "question": "الفرق بين الدفع النقدي والاعتراف بالمصروف هو أن:",
    "choices": [
      "الدفع حدث نقدي، والاعتراف حدث محاسبي يحدد الفترة المناسبة",
      "هما شيء واحد دائما",
      "الاعتراف لا يرتبط بالقوائم المالية",
      "الدفع لا يسجل محاسبيا"
    ],
    "correct": 0,
    "explanation": "قد يحدث الدفع في فترة والاعتراف بالمصروف في فترة أخرى بحسب الاستحقاق."
  },
  {
    "question": "أي من الآتي يعد خطأ شائعا؟",
    "choices": [
      "اعتبار كل مدفوع نقدي مصروفا فوريا",
      "التمييز بين الأصل والمصروف",
      "الاعتراف بالرواتب المستحقة",
      "ربط تكلفة المبيعات ببيع المخزون"
    ],
    "correct": 0,
    "explanation": "ليس كل مدفوع نقدي مصروفا فوريا، فقد يمثل أصلا أو منفعة مستقبلية."
  },
  {
    "question": "الإهلاك يمثل:",
    "choices": [
      "توزيع تكلفة أصل طويل الأجل على الفترات المستفيدة",
      "دفعا نقديا فقط",
      "ربحا من بيع أصل",
      "زيادة في حقوق الملكية"
    ],
    "correct": 0,
    "explanation": "الإهلاك يعبر عن الاعتراف المنظم بالمصروف على عدة فترات عند استخدام أصل طويل الأجل."
  },
  {
    "question": "إذا انخفضت القيمة القابلة للاسترداد لأصل عن قيمته الدفترية، فقد ينشأ:",
    "choices": [
      "خسارة انخفاض قيمة تعترف في الفترة",
      "إيراد جديد",
      "تكلفة مبيعات مباشرة",
      "مساهمة من الملاك"
    ],
    "correct": 0,
    "explanation": "عند انخفاض قيمة الأصل اقتصاديا قد تعترف المنشأة بخسارة انخفاض قيمة تخص الفترة."
  },
  {
    "question": "أفضل وصف للاعتراف بالمصروفات هو أنه:",
    "choices": [
      "تحميل الفترة بما يخصها من أعباء وفقا لطبيعة المنفعة أو الالتزام",
      "الاعتماد الكامل على النقدية فقط",
      "تسجيل كل بند في نفس تاريخ الدفع",
      "إلغاء التقدير المهني"
    ],
    "correct": 0,
    "explanation": "هذا الوصف يجمع بين جوهر الاستحقاق وفهم طبيعة المنفعة أو الالتزام."
  },
  {
    "question": "إذا اشترت المنشأة خدمة تخص الفترة الحالية ولم تسددها بعد، فإن المعالجة الصحيحة غالبا هي:",
    "choices": [
      "عدم تسجيلها حتى الدفع",
      "تسجيل مصروف مع التزام مستحق",
      "تسجيلها كأصل دائم",
      "تجاهلها حتى نهاية السنة التالية"
    ],
    "correct": 1,
    "explanation": "إذا كانت الخدمة تخص الفترة الحالية، فيجب الاعتراف بالمصروف والالتزام المستحق حتى لو لم يتم الدفع."
  },
  {
    "question": "أي من الآتي لا يساعد على صدق صافي الربح؟",
    "choices": [
      "تأخير الاعتراف بمصروفات تخص الفترة",
      "الالتزام بأساس الاستحقاق",
      "التمييز بين الأصل والمصروف",
      "توزيع تكلفة الأصل على فترات الاستفادة"
    ],
    "correct": 0,
    "explanation": "تأخير الاعتراف بالمصروفات يؤدي إلى تضخيم الأرباح ويضعف صدق صافي الربح."
  },
  {
    "question": "في التحليل المحاسبي، الاعتراف بالمصروفات يرتبط مباشرة بـ:",
    "choices": [
      "جودة الأرباح وعدالة تحميل الفترات",
      "عدد العملاء فقط",
      "رأس المال فقط",
      "الالتزامات طويلة الأجل فقط"
    ],
    "correct": 0,
    "explanation": "الاعتراف السليم بالمصروفات أساسي لجودة الأرباح وعدالة القوائم المالية بين الفترات."
  },
  {
    "question": "أي من الآتي يوضح العلاقة بين الاعتراف بالمصروفات وقائمة الدخل؟",
    "choices": [
      "الاعتراف الصحيح بالمصروفات يحدد نتيجة الفترة بدقة",
      "المصروفات لا تؤثر في قائمة الدخل",
      "المصروفات تظهر فقط في قائمة المركز المالي",
      "الاعتراف بالمصروفات لا علاقة له بالربح"
    ],
    "correct": 0,
    "explanation": "المصروفات عنصر رئيسي في قائمة الدخل، وأي خطأ في توقيتها أو قياسها يشوه نتيجة الفترة."
  },
  {
    "question": "في النهاية، فهم الاعتراف بالمصروفات يساعد الطالب على:",
    "choices": [
      "تمييز متى تحمل الفترة بالمصروف ومتى يثبت أصل أو التزام",
      "الاعتماد على الدفع فقط",
      "إلغاء الحاجة إلى المعايير",
      "تجاهل طبيعة المنفعة الاقتصادية"
    ],
    "correct": 0,
    "explanation": "جوهر الموضوع هو فهم متى تتحول النفقة إلى مصروف، ومتى تبقى أصلا أو تنشئ التزاما."
  }
]
