[
  {
    "question": "ما المقصود بتكلفة السلع المباعة؟",
    "choices": [
      "تكلفة السلع التي اكتمل تصنيعها خلال الفترة",
      "تكلفة المنتجات التي بيعت خلال الفترة",
      "إجمالي المبيعات خلال الفترة",
      "إجمالي المشتريات الصناعية"
    ],
    "correct": 1,
    "explanation": "تكلفة السلع المباعة تتعلق بالسلع التي خرجت من المخزون بسبب البيع."
  },
  {
    "question": "ما الفرق الأساسي بين تكلفة السلع المباعة وتكلفة السلع المصنعة؟",
    "choices": [
      "لا يوجد فرق",
      "الأولى تخص البيع، والثانية تخص الإكمال الصناعي",
      "الأولى تخص المواد الخام، والثانية تخص النقدية",
      "الأولى تخص الإدارة، والثانية تخص التسويق"
    ],
    "correct": 1,
    "explanation": "تكلفة السلع المصنعة تعبر عن السلع المكتملة، أما تكلفة السلع المباعة فتعبر عما بيع منها."
  },
  {
    "question": "الصيغة العامة لتكلفة السلع المباعة في المنشأة الصناعية هي:",
    "choices": [
      "المبيعات - المصروفات الإدارية",
      "الإنتاج التام أول الفترة + تكلفة السلع المصنعة - الإنتاج التام آخر الفترة",
      "المواد المباشرة + الأجور المباشرة فقط",
      "الإنتاج تحت التشغيل أول الفترة + آخر الفترة"
    ],
    "correct": 1,
    "explanation": "هذه هي المعادلة الأساسية لحساب تكلفة السلع المباعة في البيئة الصناعية."
  },
  {
    "question": "لماذا يُضاف رصيد الإنتاج التام أول الفترة عند حساب تكلفة السلع المباعة؟",
    "choices": [
      "لأنه غير متاح للبيع",
      "لأنه يمثل منتجات كانت متاحة للبيع خلال الفترة",
      "لأنه يمثل مصروفًا إداريًا",
      "لأنه يساوي المبيعات"
    ],
    "correct": 1,
    "explanation": "مخزون أول الفترة من الإنتاج التام كان متاحًا للبيع خلال الفترة الحالية."
  },
  {
    "question": "لماذا يُطرح رصيد الإنتاج التام آخر الفترة؟",
    "choices": [
      "لأنه يمثل منتجات لم تُبع بعد",
      "لأنه يمثل مواد خام مستخدمة",
      "لأنه يمثل مبيعات مؤجلة",
      "لأنه لا يؤثر على الربح"
    ],
    "correct": 0,
    "explanation": "المنتجات التامة التي بقيت في آخر الفترة لا تدخل ضمن تكلفة السلع المباعة."
  },
  {
    "question": "إذا كانت المبيعات 100,000 ريال وتكلفة السلع المباعة 62,000 ريال، فإن مجمل الربح يساوي:",
    "choices": [
      "38,000 ريال",
      "62,000 ريال",
      "100,000 ريال",
      "162,000 ريال"
    ],
    "correct": 0,
    "explanation": "مجمل الربح = 100,000 - 62,000 = 38,000 ريال."
  },
  {
    "question": "أي من الآتي يعد خطأ شائعًا في حساب تكلفة السلع المباعة؟",
    "choices": [
      "التمييز بينها وبين المبيعات",
      "إضافة مخزون الإنتاج التام أول الفترة",
      "الخلط بينها وبين تكلفة السلع المصنعة",
      "طرح مخزون الإنتاج التام آخر الفترة"
    ],
    "correct": 2,
    "explanation": "الخلط بين تكلفة السلع المباعة وتكلفة السلع المصنعة من أكثر الأخطاء شيوعًا."
  },
  {
    "question": "إذا كان رصيد الإنتاج التام أول الفترة 9,000 ريال، وتكلفة السلع المصنعة 41,000 ريال، ورصيد الإنتاج التام آخر الفترة 7,000 ريال، فإن تكلفة السلع المباعة تساوي:",
    "choices": [
      "34,000 ريال",
      "41,000 ريال",
      "43,000 ريال",
      "57,000 ريال"
    ],
    "correct": 2,
    "explanation": "تكلفة السلع المباعة = 9,000 + 41,000 - 7,000 = 43,000 ريال."
  },
  {
    "question": "تكلفة السلع المباعة تؤثر مباشرة على:",
    "choices": [
      "مجمل الربح",
      "عدد الموظفين",
      "الاستهلاك السنوي",
      "رأس المال المدفوع"
    ],
    "correct": 0,
    "explanation": "مجمل الربح يحسب بطرح تكلفة السلع المباعة من المبيعات."
  },
  {
    "question": "أي عبارة أدق بشأن العلاقة بين تكلفة السلع المباعة والمخزون؟",
    "choices": [
      "لا علاقة بينهما",
      "هي تكلفة انتقلت من المخزون إلى قائمة الدخل نتيجة البيع",
      "هي تكلفة انتقلت من النقدية إلى المخزون",
      "هي مصروف إداري ثابت"
    ],
    "correct": 1,
    "explanation": "عند بيع السلع تخرج تكلفتها من المخزون وتدخل إلى قائمة الدخل."
  },
  {
    "question": "إذا لم يُطرح رصيد الإنتاج التام آخر الفترة، فإن النتيجة غالبًا تكون:",
    "choices": [
      "تخفيض تكلفة السلع المباعة",
      "تضخيم تكلفة السلع المباعة",
      "عدم تغير مجمل الربح",
      "تحويل الإنتاج التام إلى مواد خام"
    ],
    "correct": 1,
    "explanation": "لأن منتجات لم تبع بعد ستدخل خطأ ضمن تكلفة السلع المباعة."
  },
  {
    "question": "أي من الآتي لا يدخل ضمن تكلفة السلع المباعة؟",
    "choices": [
      "تكلفة المنتجات التامة التي بيعت",
      "رصيد الإنتاج التام أول الفترة ضمن السلع المتاحة للبيع",
      "المصروفات الإدارية العامة غير المرتبطة بالإنتاج",
      "تكلفة السلع المصنعة خلال الفترة"
    ],
    "correct": 2,
    "explanation": "المصروفات الإدارية ليست جزءًا من تكلفة السلع المباعة."
  },
  {
    "question": "ارتفاع تكلفة السلع المباعة قد يكون طبيعيًا إذا صاحبه:",
    "choices": [
      "ارتفاع في حجم المبيعات",
      "اختفاء المبيعات تمامًا",
      "انعدام الإنتاج",
      "عدم وجود مخزون أول مدة"
    ],
    "correct": 0,
    "explanation": "زيادة المبيعات قد تؤدي طبيعيًا إلى ارتفاع تكلفة السلع المباعة."
  },
  {
    "question": "أي عبارة تشرح الفرق بين المبيعات وتكلفة السلع المباعة؟",
    "choices": [
      "كلاهما يقاس بسعر البيع",
      "كلاهما يقاس بالتكلفة الصناعية",
      "المبيعات تقاس بسعر البيع، وتكلفة السلع المباعة تقاس بتكلفة المنتج المباع",
      "كلاهما لا يؤثر على الربح"
    ],
    "correct": 2,
    "explanation": "هذا هو الفرق الجوهري بين الإيراد والتكلفة في التحليل المالي."
  },
  {
    "question": "إذا حسب محاسب تكلفة السلع المباعة من خلال المبيعات فقط، فإنه يكون قد:",
    "choices": [
      "طبق المعالجة الصحيحة",
      "خلط بين الإيراد والتكلفة",
      "حسب مجمل الربح",
      "حسب تكلفة السلع المصنعة"
    ],
    "correct": 1,
    "explanation": "المبيعات تمثل الإيراد، وليست تكلفة السلع المباعة."
  }
]
