[
  {
    "question": "ما المقصود بطبيعة الدخل؟",
    "choices": [
      "فهم ماهية الدخل ومصدره وهل هو من النشاط العادي أم من بنود أخرى",
      "مجرد معرفة المبلغ النقدي المقبوض",
      "حساب تكلفة المبيعات فقط",
      "معرفة عدد الأسهم فقط"
    ],
    "correct": 0,
    "explanation": "طبيعة الدخل تعني فهم مصدره وصفته الاقتصادية والمحاسبية، لا مجرد معرفة قيمته النقدية."
  },
  {
    "question": "أي عبارة صحيحة؟",
    "choices": [
      "الدخل أوسع من الإيراد",
      "الإيراد أوسع من الدخل",
      "لا يوجد فرق بين الدخل والإيراد",
      "الدخل يساوي النقدية فقط"
    ],
    "correct": 0,
    "explanation": "الدخل يشمل الإيرادات والمكاسب، ولذلك فهو أوسع من الإيراد."
  },
  {
    "question": "أي من الآتي يمثل دخلا في صورة مكسب؟",
    "choices": [
      "بيع بضاعة للعميل ضمن النشاط المعتاد",
      "تقديم خدمة استشارية ضمن النشاط الأساسي",
      "ربح بيع أصل ثابت",
      "تحصيل ذمة مدينة قديمة"
    ],
    "correct": 2,
    "explanation": "ربح بيع الأصل الثابت يعد مكسبا، وهو صورة من صور الدخل لكن ليس إيرادا تشغيليا معتادا."
  },
  {
    "question": "إذا قدمت المنشأة خدمة في ديسمبر وتحصلت النقدية في يناير، فإن الدخل قد يعترف به:",
    "choices": [
      "في ديسمبر إذا تحققت شروط الاعتراف",
      "فقط في يناير عند القبض",
      "فقط عند نهاية السنة التالية",
      "لا يعترف به إطلاقا"
    ],
    "correct": 0,
    "explanation": "أساس الاستحقاق يعني أن الاعتراف قد يتم عند تحقق الأداء لا عند القبض فقط."
  },
  {
    "question": "الدفعة المقدمة عن خدمة مستقبلية تعد عند القبض:",
    "choices": [
      "دخلا كاملا فوريا",
      "التزاما إلى أن تقدم الخدمة",
      "ربحا محققا نهائيا",
      "تكلفة مبيعات"
    ],
    "correct": 1,
    "explanation": "القبض المسبق لا يعني تحقق الدخل إذا لم تنفذ الخدمة بعد."
  },
  {
    "question": "أي معيار يرتبط أكثر بفهم الإيراد الناتج من عقود مع العملاء ضمن طبيعة الدخل؟",
    "choices": [
      "IFRS 15",
      "IAS 2",
      "IAS 16",
      "IAS 21"
    ],
    "correct": 0,
    "explanation": "`IFRS 15` ينظم الإيرادات الناتجة عن عقود مع العملاء، وهي جزء مهم من فهم طبيعة الدخل."
  },
  {
    "question": "أي معيار يرتبط أكثر بعرض طبيعة الدخل داخل القوائم المالية؟",
    "choices": [
      "IAS 1",
      "IAS 7",
      "IAS 23",
      "IAS 40"
    ],
    "correct": 0,
    "explanation": "`IAS 1` يضع الإطار العام لعرض البنود داخل قائمة الربح أو الخسارة بشكل عادل وواضح."
  },
  {
    "question": "الفرق بين الدخل النقدي والدخل المحاسبي هو أن:",
    "choices": [
      "الدخل المحاسبي قد يتحقق قبل القبض أو بعده وفق أساس الاستحقاق",
      "كلاهما شيء واحد دائما",
      "الدخل النقدي أوسع من المحاسبي دائما",
      "الدخل المحاسبي لا يعتمد على أي معايير"
    ],
    "correct": 0,
    "explanation": "الدخل المحاسبي يعتمد على الاستحقاق، بينما الدخل النقدي يعتمد على المقبوضات الفعلية."
  },
  {
    "question": "أي من الآتي يمثل دخلا من النشاط العادي؟",
    "choices": [
      "مبيعات البضاعة في منشأة تجارية",
      "ربح بيع أرض إدارية",
      "خسارة انخفاض قيمة أصل",
      "مصروف فوائد"
    ],
    "correct": 0,
    "explanation": "مبيعات البضاعة تمثل إيرادا من النشاط العادي، وهو من أهم صور الدخل التشغيلي."
  },
  {
    "question": "أي من الآتي يعبر عن أهمية طبيعة الدخل في التحليل المالي؟",
    "choices": [
      "تساعد على تقييم جودة الأرباح ومصدرها",
      "تلغي الحاجة إلى قائمة الدخل",
      "تجعل كل البنود متشابهة",
      "لا فائدة لها في التحليل"
    ],
    "correct": 0,
    "explanation": "تحليل طبيعة الدخل يساعد في معرفة ما إذا كانت الأرباح ناتجة من النشاط الأساسي أو من بنود أخرى."
  },
  {
    "question": "أي من الآتي يعد خطأ شائعا؟",
    "choices": [
      "اعتبار كل دخل إيرادا تشغيليا",
      "التمييز بين الإيراد والمكسب",
      "فهم أثر أساس الاستحقاق",
      "ربط العرض بـ `IAS 1`"
    ],
    "correct": 0,
    "explanation": "ليس كل دخل إيرادا تشغيليا، فبعضه يعد مكاسب أو بنودا أخرى مختلفة الطبيعة."
  },
  {
    "question": "إذا حققت المنشأة ربحا كبيرا من بيع مبنى، فإن ذلك يعني بالضرورة أن:",
    "choices": [
      "الأداء التشغيلي الأساسي قوي جدا",
      "هناك دخلا من بند غير تشغيلي غالبا",
      "هذا البند يعد إيرادا عاديا",
      "لا أثر له على التحليل"
    ],
    "correct": 1,
    "explanation": "الربح من بيع المبنى قد يكون بندا مهما، لكنه لا يعني بالضرورة قوة النشاط التشغيلي الأساسي."
  },
  {
    "question": "أي عبارة أدق؟",
    "choices": [
      "طبيعة الدخل لا تتحدد بالمقدار فقط، بل بالمصدر وطريقة العرض أيضا",
      "طبيعة الدخل تحدد فقط بحجم المبلغ",
      "الدخل لا علاقة له بالعرض المحاسبي",
      "كل البنود الموجبة تعني الشيء نفسه"
    ],
    "correct": 0,
    "explanation": "المصدر والصفة وطريقة العرض عناصر أساسية في فهم طبيعة الدخل."
  },
  {
    "question": "إذا كان البند الموجب يعرض في الدخل الشامل الآخر بحسب معيار معين، فإن ذلك يعني أن:",
    "choices": [
      "طبيعة البند وموضع عرضه يحددان بالمعيار المختص",
      "البند ليس له أي طبيعة اقتصادية",
      "كل البنود الموجبة يجب أن تظهر في الإيرادات",
      "لا يجوز الاعتراف به إطلاقا"
    ],
    "correct": 0,
    "explanation": "بعض صور الدخل أو الزيادة الاقتصادية قد تعرض في الدخل الشامل الآخر بحسب المعيار المنظم لها."
  },
  {
    "question": "أي من الآتي يوضح الفرق بين الإيراد والمكسب؟",
    "choices": [
      "الإيراد يرتبط غالبا بالنشاط العادي، أما المكسب فقد ينشأ من معاملة أخرى",
      "المكسب دائما من المبيعات العادية",
      "الإيراد لا يؤثر في الربح",
      "لا فرق بينهما"
    ],
    "correct": 0,
    "explanation": "هذا هو الفرق الجوهري بين الإيراد والمكسب في التحليل المحاسبي."
  },
  {
    "question": "أفضل وصف لطبيعة الدخل هو أنها:",
    "choices": [
      "مفهوم تحليلي يوضح مصدر الدخل وخصائصه المحاسبية",
      "رقم نقدي فقط",
      "تكلفة تخص المخزون",
      "أصل غير متداول"
    ],
    "correct": 0,
    "explanation": "طبيعة الدخل تساعد على فهم المصدر والتصنيف والجودة والعرض المحاسبي."
  },
  {
    "question": "إذا قبضت المنشأة نقدا من العميل قبل أداء الخدمة، فإن التصنيف الصحيح عند القبض مباشرة هو:",
    "choices": [
      "ليس دخلا محققا بالكامل بعد",
      "إيراد نهائي كامل",
      "مكسب رأسمالي",
      "خسارة عرضية"
    ],
    "correct": 0,
    "explanation": "لا يعد الدخل متحققا بالكامل إذا لم تنفذ الخدمة بعد، حتى لو تم القبض النقدي."
  },
  {
    "question": "أي من الآتي يجعل جودة الأرباح أعلى عادة؟",
    "choices": [
      "أن يكون الجزء الأكبر من الدخل ناتجا من النشاط العادي المتكرر",
      "أن يعتمد الدخل كله على بيع الأصول",
      "أن يكون أغلب الدخل من بنود عرضية",
      "أن يتغير التصنيف كل فترة دون مبرر"
    ],
    "correct": 0,
    "explanation": "كلما كان الدخل ناتجا من النشاط الأساسي المتكرر، كانت جودة الأرباح أعلى من الناحية التحليلية."
  },
  {
    "question": "أي من الآتي لا يعد هدفا من دراسة طبيعة الدخل؟",
    "choices": [
      "إخفاء مصدر الربحية الحقيقي",
      "فهم جودة الأرباح",
      "تمييز الدخل التشغيلي من غيره",
      "تحسين التحليل المالي"
    ],
    "correct": 0,
    "explanation": "الهدف من دراسة طبيعة الدخل هو زيادة الوضوح والتحليل، لا إخفاء المصدر الحقيقي للربحية."
  },
  {
    "question": "في التحليل النهائي، فهم طبيعة الدخل يساعد على:",
    "choices": [
      "الحكم على استدامة الأداء وربحية المنشأة بصورة أدق",
      "إلغاء الحاجة إلى قراءة القوائم",
      "الاكتفاء بالرقم النهائي فقط",
      "تجاهل جميع الإيضاحات"
    ],
    "correct": 0,
    "explanation": "فهم طبيعة الدخل يعطي صورة أدق عن الاستدامة والجودة ومصدر الأداء."
  }
]
